Driver2Comm/__init__.py
Driver2Comm/association_test.py
Driver2Comm/Downstream_analysis/CytoTalk_network.py
Driver2Comm/Downstream_analysis/Visualization.py
Driver2Comm/Downstream_analysis/__init__.py
Driver2Comm/Downstream_analysis/_downstream_analysis.py
Driver2Comm/data/__init__.py
Driver2Comm/data/load_data.py
Driver2Comm/data/lrp_human.csv
Driver2Comm/data/Driver2Comm_output/BrcaExternalSup14.csv
Driver2Comm/data/Driver2Comm_output/BrcaInternal.csv
Driver2Comm/data/Driver2Comm_output/PDACExternalSup14.csv
Driver2Comm/data/Driver2Comm_output/PDACExternalSup8.csv
Driver2Comm/data/Driver2Comm_output/PDACInternal.csv
Driver2Comm/model/__init__.py
Driver2Comm/model/association_test.py
Driver2Comm/model/external.py
Driver2Comm/model/gSpan.py
Driver2Comm/model/graph.py
Driver2Comm/model/model.py
Driver2Comm/preprocessing/__init__.py
Driver2Comm/preprocessing/preprocessing.py
Driver2Comm-0.3.0.dist-info/LICENSE
Driver2Comm-0.3.0.dist-info/METADATA
Driver2Comm-0.3.0.dist-info/WHEEL
Driver2Comm-0.3.0.dist-info/top_level.txt
Driver2Comm-0.3.0.dist-info/RECORD
