Metadata-Version: 2.1
Name: Driver2Comm
Version: 0.3.0
Summary: A computational framework for associating cancer cell-intrinsic driver genes with -extrinsic cell-cell communication
Home-page: https://github.com/xierunzhi
Author: Runzhi Xie, Junping Li, Yuxuan Hu*, Gao Lin*
Author-email: rzxie1998@gmail.com
Maintainer: Runzhi Xie
Maintainer-email: rzxie1998@gmail.com
License: MIT Licence
Keywords: scRNA-seq,cell-cell communication,cancer driver gene,tumor microenvironment
Platform: any
Classifier: Programming Language :: Python :: 3
Classifier: License :: OSI Approved :: MIT License
Classifier: Operating System :: OS Independent
Requires-Python: >=3.8
License-File: LICENSE
Requires-Dist: numpy
Requires-Dist: pandas
Requires-Dist: statsmodels
Requires-Dist: networkx
Requires-Dist: matplotlib
Requires-Dist: scipy
